amazon_review_analyzer/__init__.py
amazon_review_analyzer/reviews.py
amazon_review_analyzer-1.1.1.dist-info/METADATA
amazon_review_analyzer-1.1.1.dist-info/WHEEL
amazon_review_analyzer-1.1.1.dist-info/top_level.txt
amazon_review_analyzer-1.1.1.dist-info/RECORD
