Metadata-Version: 2.1
Name: amazon-review-analyzer
Version: 1.1.1
Summary: Amazon Product Reviews Analyzer
Author: Krishna Chaitanya
Author-email: <chaitu.gorle@gmail.com>
Keywords: python,amazon,review,analyzer,sentiment,analysis,amazon review analyzer
